agent_compose_kit/__init__.py
agent_compose_kit/compose.py
agent_compose_kit/main.py
agent_compose_kit/paths.py
agent_compose_kit/_retired/agents/builder.py
agent_compose_kit/_retired/agents/builders_registry.py
agent_compose_kit/_retired/agents/registry.py
agent_compose_kit/_retired/api/public.py
agent_compose_kit/_retired/runtime/supervisor.py
agent_compose_kit/_retired/services/factory.py
agent_compose_kit/_retired/tools/loader.py
agent_compose_kit/_retired/tools/mcp_registry.py
agent_compose_kit/_retired/tools/openapi_registry.py
agent_compose_kit/_retired/tools/registry.py
agent_compose_kit/agents/tools.py
agent_compose_kit/config/models.py
agent_compose_kit/graph/build.py
agent_compose_kit/lock/__init__.py
agent_compose_kit/lock/plan.py
agent_compose_kit/quickfix/__init__.py
agent_compose_kit/quickfix/fixes.py
agent_compose_kit/registries/agents.py
agent_compose_kit/registries/aliases.py
agent_compose_kit/registries/tools.py
agent_compose_kit/registry/fs.py
agent_compose_kit/tools/builders.py
agent_compose_kit-0.5.0.dist-info/METADATA
agent_compose_kit-0.5.0.dist-info/WHEEL
agent_compose_kit-0.5.0.dist-info/licenses/LICENSE
agent_compose_kit-0.5.0.dist-info/RECORD
