Metadata-Version: 2.4
Name: agent-compose-kit
Version: 0.5.0
Summary: Core library to compose, validate, and run ADK agent systems from YAML.
Project-URL: Homepage, https://github.com/DeadMeme5441/agent-compose-kit
Project-URL: Repository, https://github.com/DeadMeme5441/agent-compose-kit
Author: DeadMeme5441
License: MIT
License-File: LICENSE
Classifier: Development Status :: 3 - Alpha
Classifier: License :: OSI Approved :: MIT License
Classifier: Operating System :: OS Independent
Classifier: Programming Language :: Python :: 3
Classifier: Programming Language :: Python :: 3.12
Classifier: Topic :: Software Development :: Libraries
Requires-Python: >=3.12
Requires-Dist: google-adk
Requires-Dist: google-adk-extras
Requires-Dist: litellm
Requires-Dist: pydantic
Requires-Dist: pyyaml
Provides-Extra: dev
Requires-Dist: build; extra == 'dev'
Requires-Dist: pytest; extra == 'dev'
Requires-Dist: ruff; extra == 'dev'
Requires-Dist: twine; extra == 'dev'
Provides-Extra: docs
Requires-Dist: mkdocs; extra == 'docs'
Requires-Dist: mkdocs-llmstxt; extra == 'docs'
Requires-Dist: mkdocs-material; extra == 'docs'
Requires-Dist: pymdown-extensions; extra == 'docs'
Provides-Extra: tools
Requires-Dist: mcp; extra == 'tools'
